salt/__init__.py
salt/main.py
salt/modelwrapper.py
salt/stypes.py
salt/callbacks/__init__.py
salt/callbacks/checkpoint.py
salt/callbacks/gradient_logger.py
salt/callbacks/integrated_gradients_writer.py
salt/callbacks/maskformer_metrics.py
salt/callbacks/performancewriter.py
salt/callbacks/predictionwriter.py
salt/callbacks/saveconfig.py
salt/callbacks/weight_logger.py
salt/configs/Baseline_Xbb.yaml
salt/configs/DL1.yaml
salt/configs/Dipz.yaml
salt/configs/GATv2.yaml
salt/configs/GN1.yaml
salt/configs/GN2.yaml
salt/configs/GN2X.yaml
salt/configs/GN2XE.yaml
salt/configs/GN2XTau.yaml
salt/configs/GN2X_qcdsplit.yaml
salt/configs/GN2_charded_neutral_loose_aux.yaml
salt/configs/GN2_extended.yaml
salt/configs/GN2_muP.yaml
salt/configs/GN2_open_data.yaml
salt/configs/GN2_tracks_neutral_CA.yaml
salt/configs/GN2_tracks_neutral_SA_aux.yaml
salt/configs/GN2emu.yaml
salt/configs/MaskFormer.yaml
salt/configs/PLITel.yaml
salt/configs/SubjetXbb.yaml
salt/configs/TPLTmu.yaml
salt/configs/base.yaml
salt/configs/dips.yaml
salt/configs/encoder-v2.yaml
salt/configs/event_classifier.yaml
salt/configs/flow.yaml
salt/configs/hitz.yaml
salt/configs/nan_regression.yaml
salt/configs/regression.yaml
salt/configs/regression_gaussian.yaml
salt/configs/tutorial.yaml
salt/data/__init__.py
salt/data/datamodules.py
salt/data/datasets.py
salt/data/edge_features.py
salt/data/samplers.py
salt/data/transforms.py
salt/metrics/__init__.py
salt/models/__init__.py
salt/models/attention.py
salt/models/dense.py
salt/models/featurewise.py
salt/models/initnet.py
salt/models/inputnorm.py
salt/models/layernorm.py
salt/models/maskformer.py
salt/models/maskformer_loss.py
salt/models/matcher.py
salt/models/pooling.py
salt/models/posenc.py
salt/models/r21xbb.py
salt/models/saltmodel.py
salt/models/task.py
salt/models/transformer.py
salt/models/transformer_v2.py
salt/onnx/check.py
salt/onnx/to_onnx.py
salt/submit/condor_handler.py
salt/submit/slurm_handler.py
salt/submit/submit_htcondor.py
salt/submit/submit_slurm.py
salt_ml-0.10.dist-info/licenses/LICENSE
salt_ml-0.10.dist-info/METADATA
salt_ml-0.10.dist-info/WHEEL
salt_ml-0.10.dist-info/entry_points.txt
salt_ml-0.10.dist-info/top_level.txt
salt_ml-0.10.dist-info/RECORD
